{
	"info": {
		"_postman_id": "8f9b2371-5cdf-46b4-9e0e-28b382e9fc26",
		"name": "Assignment api",
		"schema": "https://schema.getpostman.com/json/collection/v2.1.0/collection.json"
	},
	"item": [
		{
			"name": "Get Token",
			"event": [
				{
					"listen": "test",
					"script": {
						"exec": [
							"pm.test(\"Status code is 200\", function () {",
							"    pm.response.to.have.status(200);",
							"});",
							"const response = pm.response.json();",
							"pm.globals.set(\"token\", response.token);"
						],
						"type": "text/javascript"
					}
				},
				{
					"listen": "prerequest",
					"script": {
						"exec": [
							""
						],
						"type": "text/javascript"
					}
				}
			],
			"request": {
				"method": "POST",
				"header": [
					{
						"key": "Authorization",
						"value": "Token c70cf75e8cb42786c5fc61acea32189433a24a6d",
						"type": "text"
					}
				],
				"body": {
					"mode": "raw",
					"raw": "{\n    \"username\": \"gopinath\",\n    \"password\": \"g1234567\"\n}",
					"options": {
						"raw": {
							"language": "json"
						}
					}
				},
				"url": {
					"raw": "{{baseUrl}}/api-token-auth/",
					"host": [
						"{{baseUrl}}"
					],
					"path": [
						"api-token-auth",
						""
					]
				}
			},
			"response": []
		},
		{
			"name": "Get list of assignments",
			"event": [
				{
					"listen": "test",
					"script": {
						"exec": [
							"const response = pm.response.json();   ",
							"pm.globals.set(\"assignmentid\", response[0].id)",
							"pm.test(\"Status code is 200\", function () {",
							"    pm.response.to.have.status(200);",
							"});",
							"",
							""
						],
						"type": "text/javascript"
					}
				}
			],
			"protocolProfileBehavior": {
				"disableBodyPruning": true
			},
			"request": {
				"method": "GET",
				"header": [
					{
						"key": "Authorization",
						"value": "Token {{token}}",
						"type": "text"
					}
				],
				"body": {
					"mode": "raw",
					"raw": "",
					"options": {
						"raw": {
							"language": "json"
						}
					}
				},
				"url": {
					"raw": "{{baseUrl}}/viewset/assignments/",
					"host": [
						"{{baseUrl}}"
					],
					"path": [
						"viewset",
						"assignments",
						""
					]
				}
			},
			"response": []
		},
		{
			"name": "Get single assignment",
			"event": [
				{
					"listen": "test",
					"script": {
						"exec": [
							"pm.test(\"Status code is 200\", function () {",
							"    pm.response.to.have.status(200);",
							"});"
						],
						"type": "text/javascript"
					}
				},
				{
					"listen": "prerequest",
					"script": {
						"exec": [
							""
						],
						"type": "text/javascript"
					}
				}
			],
			"protocolProfileBehavior": {
				"disableBodyPruning": true
			},
			"request": {
				"method": "GET",
				"header": [
					{
						"key": "Authorization",
						"value": "Token {{token}}",
						"type": "text"
					}
				],
				"body": {
					"mode": "raw",
					"raw": "",
					"options": {
						"raw": {
							"language": "json"
						}
					}
				},
				"url": {
					"raw": "{{baseUrl}}/viewset/assignments/:id/",
					"host": [
						"{{baseUrl}}"
					],
					"path": [
						"viewset",
						"assignments",
						":id",
						""
					],
					"variable": [
						{
							"key": "id",
							"value": "{{assignmentid}}"
						}
					]
				}
			},
			"response": []
		},
		{
			"name": "Get first assignment to submit",
			"event": [
				{
					"listen": "test",
					"script": {
						"exec": [
							"pm.test(\"Status code is 200\", function () {",
							"    pm.response.to.have.status(200);",
							"});"
						],
						"type": "text/javascript"
					}
				},
				{
					"listen": "prerequest",
					"script": {
						"exec": [
							""
						],
						"type": "text/javascript"
					}
				}
			],
			"protocolProfileBehavior": {
				"disableBodyPruning": true
			},
			"request": {
				"auth": {
					"type": "basic",
					"basic": [
						{
							"key": "password",
							"value": "g1234567",
							"type": "string"
						},
						{
							"key": "username",
							"value": "gopinath",
							"type": "string"
						}
					]
				},
				"method": "GET",
				"header": [
					{
						"warning": "This is a duplicate header and will be overridden by the Authorization header generated by Postman.",
						"key": "Authorization",
						"value": "Token {{token}}",
						"type": "text"
					}
				],
				"body": {
					"mode": "raw",
					"raw": "",
					"options": {
						"raw": {
							"language": "json"
						}
					}
				},
				"url": {
					"raw": "{{baseUrl}}/viewset/assignments/newest/",
					"host": [
						"{{baseUrl}}"
					],
					"path": [
						"viewset",
						"assignments",
						"newest",
						""
					]
				}
			},
			"response": []
		},
		{
			"name": "Create assignment",
			"event": [
				{
					"listen": "test",
					"script": {
						"exec": [
							"pm.test(\"Status code is 201\", function () {",
							"    pm.response.to.have.status(201);",
							"});"
						],
						"type": "text/javascript"
					}
				},
				{
					"listen": "prerequest",
					"script": {
						"exec": [
							"const subject = [\"English\", \"Tamil\", \"Maths\", \"Physics\", \"Chemistry\", \"Biology\"];",
							"const choice = subject[Math.floor(Math.random() * subject.length)];",
							"pm.globals.set(\"subject\", choice);",
							"function randomDate(start, end) {",
							"    var d = new Date(start.getTime() + Math.random() * (end.getTime() -                     start.getTime())),",
							"        month = '' + (d.getMonth() + 1),",
							"        day = '' + d.getDate(),",
							"        year = d.getFullYear();",
							"",
							"    if (month.length < 2) month = '0' + month;",
							"    if (day.length < 2) day = '0' + day;",
							"",
							"    return [year, month, day].join('-');",
							"}",
							"const date = randomDate(new Date(2021, 6, 23), new Date());",
							"pm.globals.set(\"due_date\", date);"
						],
						"type": "text/javascript"
					}
				}
			],
			"request": {
				"auth": {
					"type": "basic",
					"basic": [
						{
							"key": "password",
							"value": "g1234567",
							"type": "string"
						},
						{
							"key": "username",
							"value": "gopinath",
							"type": "string"
						}
					]
				},
				"method": "POST",
				"header": [
					{
						"warning": "This is a duplicate header and will be overridden by the Authorization header generated by Postman.",
						"key": "Authorization",
						"value": "Token {{token}}",
						"type": "text"
					}
				],
				"body": {
					"mode": "raw",
					"raw": "{\n    \"subject\": \"{{subject}}\",\n    \"title\": \"Respiration\",\n    \"content\": \"Draw the respiratory system of Animals\",\n    \"staff\": \"{{$randomFullName}}\",\n    \"due_date\": \"{{due_date}}\"\n}",
					"options": {
						"raw": {
							"language": "json"
						}
					}
				},
				"url": {
					"raw": "{{baseUrl}}/viewset/assignments/",
					"host": [
						"{{baseUrl}}"
					],
					"path": [
						"viewset",
						"assignments",
						""
					]
				}
			},
			"response": []
		},
		{
			"name": "Update assignment",
			"event": [
				{
					"listen": "test",
					"script": {
						"exec": [
							"pm.test(\"Status code is 200\", function () {",
							"    pm.response.to.have.status(200);",
							"});"
						],
						"type": "text/javascript"
					}
				},
				{
					"listen": "prerequest",
					"script": {
						"exec": [
							"const subject = [\"English\", \"Tamil\", \"Maths\", \"Physics\", \"Chemistry\", \"Biology\"];",
							"const choice = subject[Math.floor(Math.random() * subject.length)];",
							"pm.globals.set(\"subject\", choice);",
							"function randomDate(start, end) {",
							"    var d = new Date(start.getTime() + Math.random() * (end.getTime() -                     start.getTime())),",
							"        month = '' + (d.getMonth() + 1),",
							"        day = '' + d.getDate(),",
							"        year = d.getFullYear();",
							"",
							"    if (month.length < 2) month = '0' + month;",
							"    if (day.length < 2) day = '0' + day;",
							"",
							"    return [year, month, day].join('-');",
							"}",
							"const date = randomDate(new Date(2021, 6, 23), new Date());",
							"pm.globals.set(\"due_date\", date);"
						],
						"type": "text/javascript"
					}
				}
			],
			"request": {
				"method": "PUT",
				"header": [
					{
						"key": "Authorization",
						"value": "Token {{token}}",
						"type": "text"
					}
				],
				"body": {
					"mode": "raw",
					"raw": "{\n    \"subject\": \"{{subject}}\",\n    \"title\": \"Trignomentry\",\n    \"content\": \"1. Find HCF of 128 and 256\",\n    \"staff\": \"{{$randomFullName}}\",\n    \"due_date\": \"{{due_date}}\"\n}",
					"options": {
						"raw": {
							"language": "json"
						}
					}
				},
				"url": {
					"raw": "{{baseUrl}}/viewset/assignments/:id/",
					"host": [
						"{{baseUrl}}"
					],
					"path": [
						"viewset",
						"assignments",
						":id",
						""
					],
					"variable": [
						{
							"key": "id",
							"value": "{{assignmentid}}"
						}
					]
				}
			},
			"response": []
		},
		{
			"name": "Delete assignment",
			"event": [
				{
					"listen": "test",
					"script": {
						"exec": [
							"pm.test(\"Status code is 204\", function () {",
							"    pm.response.to.have.status(204);",
							"});",
							""
						],
						"type": "text/javascript"
					}
				}
			],
			"request": {
				"method": "DELETE",
				"header": [
					{
						"key": "Authorization",
						"value": "Token {{token}}",
						"type": "text"
					}
				],
				"body": {
					"mode": "raw",
					"raw": "",
					"options": {
						"raw": {
							"language": "json"
						}
					}
				},
				"url": {
					"raw": "{{baseUrl}}/viewset/assignments/:id/",
					"host": [
						"{{baseUrl}}"
					],
					"path": [
						"viewset",
						"assignments",
						":id",
						""
					],
					"variable": [
						{
							"key": "id",
							"value": "{{assignmentid}}"
						}
					]
				}
			},
			"response": []
		}
	]
}